ffmpeg/__init__.py
ffmpeg/_ffmpeg.py
ffmpeg/_filters.py
ffmpeg/_probe.py
ffmpeg/_run.py
ffmpeg/_utils.py
ffmpeg/_view.py
ffmpeg/dag.py
ffmpeg/nodes.py
ffmpeg_python-0.1.18.dist-info/LICENSE
ffmpeg_python-0.1.18.dist-info/METADATA
ffmpeg_python-0.1.18.dist-info/WHEEL
ffmpeg_python-0.1.18.dist-info/top_level.txt
ffmpeg_python-0.1.18.dist-info/RECORD
