Metadata-Version: 2.1
Name: ffmpeg-python
Version: 0.1.18
Summary: Python bindings for FFmpeg - with complex filtering support
Home-page: https://github.com/kkroening/ffmpeg-python
Author: Karl Kroening
Author-email: karlk@kralnet.us
License: UNKNOWN
Download-URL: https://github.com/kkroening/ffmpeg-python/archive/v0.1.18.zip
Keywords: -vf,a/v,audio,dsp,FFmpeg,ffmpeg,ffprobe,filtering,filter_complex,movie,render,signals,sound,streaming,streams,vf,video,wrapper,aac,ac3,avi,bmpflac,gif,mov,mp3,mp4,png,raw,rawvideo,wav,.aac,.ac3,.avi,.bmpflac,.gif,.mov,.mp3,.mp4,.png,.raw,.rawvideo,.wav
Platform: UNKNOWN
Classifier: Intended Audience :: Developers
Classifier: License :: OSI Approved :: Apache Software License
Classifier: Natural Language :: English
Classifier: Operating System :: OS Independent
Classifier: Programming Language :: Python
Classifier: Programming Language :: Python :: 2
Classifier: Programming Language :: Python :: 2.7
Classifier: Programming Language :: Python :: 3
Classifier: Programming Language :: Python :: 3.3
Classifier: Programming Language :: Python :: 3.4
Classifier: Programming Language :: Python :: 3.5
Classifier: Programming Language :: Python :: 3.6
Provides-Extra: dev
